LICENSE
MANIFEST.in
README.rst
setup.py
cadnaPromise/__init__.py
cadnaPromise/errors.py
cadnaPromise/install.py
cadnaPromise/logger.py
cadnaPromise/prfile.py
cadnaPromise/promise.py
cadnaPromise/run.py
cadnaPromise/utils.py
cadnaPromise.egg-info/PKG-INFO
cadnaPromise.egg-info/SOURCES.txt
cadnaPromise.egg-info/dependency_links.txt
cadnaPromise.egg-info/entry_points.txt
cadnaPromise.egg-info/not-zip-safe
cadnaPromise.egg-info/requires.txt
cadnaPromise.egg-info/top_level.txt
cadnaPromise/cache/.gitignore
cadnaPromise/cadna/README
cadnaPromise/cadna/cadna_c_half-3.1.12.tar.gz
cadnaPromise/cadna/clean.sh
cadnaPromise/cadna/run_unix.sh
cadnaPromise/cadna/run_unix_cc.sh
cadnaPromise/cadna/run_unix_cxx.sh
cadnaPromise/cadna/include/.gitattributes
cadnaPromise/cadna/include/check
cadnaPromise/cadna/include/check.cpp
cadnaPromise/cadna/include/check2.cpp
cadnaPromise/cadna/include/floatx.hpp
cadnaPromise/cadna/include/fxmath.hpp
cadnaPromise/cadna/include/half_promise.hpp
cadnaPromise/cadna/include/run.sh
cadnaPromise/deltadebug/__init__.py
cadnaPromise/deltadebug/dd.py
cadnaPromise/extra/cadnaizer
cadnaPromise/extra/input.c
cadnaPromise/extra/promise.h
cadnaPromise/extra/promise_header.h