Metadata-Version: 2.4
Name: cadnaPromise
Version: 0.4.1
Summary: Precision auto-tuning of floating-point variables in program
Home-page: https://github.com/PEQUAN/cadnaPromise
Author: LIP6 PEQUAN team
Author-email: thibault.hilaire@lip6.fr; fabienne.jezequel@lip6.fr
License: GNU General Public License v3.0
Keywords: computer arithmetic mixed-precision precision auto-tuning
Classifier: Intended Audience :: Science/Research
Classifier: Intended Audience :: Developers
Classifier: Programming Language :: C
Classifier: Programming Language :: Python
Classifier: Programming Language :: Python :: 3
Classifier: Topic :: Software Development
Classifier: Topic :: Scientific/Engineering
Classifier: Operating System :: POSIX
Classifier: Operating System :: Unix
Classifier: Operating System :: MacOS
License-File: LICENSE
Requires-Dist: colorlog
Requires-Dist: colorama
Requires-Dist: tqdm
Requires-Dist: regex
Requires-Dist: pyyaml
Requires-Dist: docopt-ng
Provides-Extra: with-doc
Requires-Dist: sphinx; extra == "with-doc"
Requires-Dist: sphinx_bootstrap_theme; extra == "with-doc"
Dynamic: author
Dynamic: author-email
Dynamic: classifier
Dynamic: description
Dynamic: description-content-type
Dynamic: home-page
Dynamic: keywords
Dynamic: license
Dynamic: license-file
Dynamic: provides-extra
Dynamic: requires-dist
Dynamic: summary
